examples/__init__.py
examples/build_dataset.py
examples/gpt2_example.py
examples/instruct_tuning.py
examples/llama2_flash_attn_monkey_patch.py
examples/llama_flash_attn_monkey_patch.py
examples/llama_xformers_attn_monkey_patch.py
examples/opt_example.py
examples/pretrain_tuning.py
examples/run_generation.py
examples/run_glue.py
examples/run_ner.py
examples/run_qa.py
examples/utils_qa.py
examples/vicuna_train.py
hift/__init__.py
hift/qatrainer.py
hift/registerCallBack.py
hift/seqtrainer.py
hift/trainer.py
hift/optimizers/__init__.py
hift/optimizers/adagrad.py
hift/optimizers/optimization.py
hift/optimizers/optimizer.py
hift/optimizers/replace_operation.py
hift/optimizers/rmsprop.py
hift/optimizers/sgd.py
hift/optimizers/torchAdam.py
hift/optimizers/torchAdamw.py
hift/optimizers/bitsandbytes/__init__.py
hift/optimizers/bitsandbytes/adagrad.py
hift/optimizers/bitsandbytes/adam.py
hift/optimizers/bitsandbytes/adamw.py
hift/optimizers/bitsandbytes/lamb.py
hift/optimizers/bitsandbytes/lars.py
hift/optimizers/bitsandbytes/lion.py
hift/optimizers/bitsandbytes/rmsprop.py
hift/optimizers/bitsandbytes/sgd.py
hift/utils/__init__.py
hift/utils/utils.py
HiFT-0.0.5.dist-info/LICENSE.md
HiFT-0.0.5.dist-info/METADATA
HiFT-0.0.5.dist-info/WHEEL
HiFT-0.0.5.dist-info/top_level.txt
HiFT-0.0.5.dist-info/RECORD
