Metadata-Version: 2.1
Name: HiFT
Version: 0.0.5
Summary: PyTorch implementation of 'HiFT: A Hierarchical Full Parameter Fine-Tuning Strategy', a memory-efficient approach to adapt a large pre-trained deep learning model.
Home-page: https://github.com/misonsky/HiFT
Author: Yongkang Liu
Author-email: misonsky@163.com
Classifier: Programming Language :: Python :: 3
Classifier: License :: OSI Approved :: MIT License
Classifier: Operating System :: OS Independent
Requires-Python: >=3.8
License-File: LICENSE.md
